{
  "metadata": {
    "source": "ENTSO-E Transparency Platform",
    "date": "2026-03-18",
    "retrieved_at": "2026-03-17T15:37:51.341717",
    "timezone": "Europe/Brussels",
    "data_points": 24,
    "resolution": "PT60M",
    "statistics": {
      "average_eur_mwh": 80.92,
      "min_eur_mwh": -1.3,
      "max_eur_mwh": 168.87,
      "min_hour": 13,
      "max_hour": 19,
      "price_spread": 170.17
    },
    "cheapest_blocks": {
      "1_hour": {
        "hour": 13,
        "time": "2026-03-18T12:00:00+01:00",
        "price": -1.3
      },
      "2_hours": {
        "start_hour": 13,
        "end_hour": 14,
        "start_time": "2026-03-18T12:00:00+01:00",
        "end_time": "2026-03-18T13:00:00+01:00",
        "average_price": -1.24,
        "hours": 2
      },
      "3_hours": {
        "start_hour": 12,
        "end_hour": 14,
        "start_time": "2026-03-18T11:00:00+01:00",
        "end_time": "2026-03-18T13:00:00+01:00",
        "average_price": -1.05,
        "hours": 3
      },
      "4_hours": {
        "start_hour": 12,
        "end_hour": 15,
        "start_time": "2026-03-18T11:00:00+01:00",
        "end_time": "2026-03-18T14:00:00+01:00",
        "average_price": -0.34,
        "hours": 4
      }
    }
  },
  "prices": [
    {
      "hour": 1,
      "datetime": "2026-03-18T00:00:00+01:00",
      "price_eur_mwh": 88.0,
      "price_eur_kwh": 0.088,
      "price_cent_kwh": 8.8
    },
    {
      "hour": 2,
      "datetime": "2026-03-18T01:00:00+01:00",
      "price_eur_mwh": 82.93,
      "price_eur_kwh": 0.0829,
      "price_cent_kwh": 8.29
    },
    {
      "hour": 3,
      "datetime": "2026-03-18T02:00:00+01:00",
      "price_eur_mwh": 85.23,
      "price_eur_kwh": 0.0852,
      "price_cent_kwh": 8.52
    },
    {
      "hour": 4,
      "datetime": "2026-03-18T03:00:00+01:00",
      "price_eur_mwh": 84.11,
      "price_eur_kwh": 0.0841,
      "price_cent_kwh": 8.41
    },
    {
      "hour": 5,
      "datetime": "2026-03-18T04:00:00+01:00",
      "price_eur_mwh": 87.38,
      "price_eur_kwh": 0.0874,
      "price_cent_kwh": 8.74
    },
    {
      "hour": 6,
      "datetime": "2026-03-18T05:00:00+01:00",
      "price_eur_mwh": 95.07,
      "price_eur_kwh": 0.0951,
      "price_cent_kwh": 9.51
    },
    {
      "hour": 7,
      "datetime": "2026-03-18T06:00:00+01:00",
      "price_eur_mwh": 114.21,
      "price_eur_kwh": 0.1142,
      "price_cent_kwh": 11.42
    },
    {
      "hour": 8,
      "datetime": "2026-03-18T07:00:00+01:00",
      "price_eur_mwh": 129.28,
      "price_eur_kwh": 0.1293,
      "price_cent_kwh": 12.93
    },
    {
      "hour": 9,
      "datetime": "2026-03-18T08:00:00+01:00",
      "price_eur_mwh": 93.91,
      "price_eur_kwh": 0.0939,
      "price_cent_kwh": 9.39
    },
    {
      "hour": 10,
      "datetime": "2026-03-18T09:00:00+01:00",
      "price_eur_mwh": 52.51,
      "price_eur_kwh": 0.0525,
      "price_cent_kwh": 5.25
    },
    {
      "hour": 11,
      "datetime": "2026-03-18T10:00:00+01:00",
      "price_eur_mwh": 9.18,
      "price_eur_kwh": 0.0092,
      "price_cent_kwh": 0.92
    },
    {
      "hour": 12,
      "datetime": "2026-03-18T11:00:00+01:00",
      "price_eur_mwh": -0.66,
      "price_eur_kwh": -0.0007,
      "price_cent_kwh": -0.07
    },
    {
      "hour": 13,
      "datetime": "2026-03-18T12:00:00+01:00",
      "price_eur_mwh": -1.3,
      "price_eur_kwh": -0.0013,
      "price_cent_kwh": -0.13
    },
    {
      "hour": 14,
      "datetime": "2026-03-18T13:00:00+01:00",
      "price_eur_mwh": -1.19,
      "price_eur_kwh": -0.0012,
      "price_cent_kwh": -0.12
    },
    {
      "hour": 15,
      "datetime": "2026-03-18T14:00:00+01:00",
      "price_eur_mwh": 1.78,
      "price_eur_kwh": 0.0018,
      "price_cent_kwh": 0.18
    },
    {
      "hour": 16,
      "datetime": "2026-03-18T15:00:00+01:00",
      "price_eur_mwh": 34.99,
      "price_eur_kwh": 0.035,
      "price_cent_kwh": 3.5
    },
    {
      "hour": 17,
      "datetime": "2026-03-18T16:00:00+01:00",
      "price_eur_mwh": 86.41,
      "price_eur_kwh": 0.0864,
      "price_cent_kwh": 8.64
    },
    {
      "hour": 18,
      "datetime": "2026-03-18T17:00:00+01:00",
      "price_eur_mwh": 131.47,
      "price_eur_kwh": 0.1315,
      "price_cent_kwh": 13.15
    },
    {
      "hour": 19,
      "datetime": "2026-03-18T18:00:00+01:00",
      "price_eur_mwh": 168.87,
      "price_eur_kwh": 0.1689,
      "price_cent_kwh": 16.89
    },
    {
      "hour": 20,
      "datetime": "2026-03-18T19:00:00+01:00",
      "price_eur_mwh": 159.65,
      "price_eur_kwh": 0.1597,
      "price_cent_kwh": 15.97
    },
    {
      "hour": 21,
      "datetime": "2026-03-18T20:00:00+01:00",
      "price_eur_mwh": 122.69,
      "price_eur_kwh": 0.1227,
      "price_cent_kwh": 12.27
    },
    {
      "hour": 22,
      "datetime": "2026-03-18T21:00:00+01:00",
      "price_eur_mwh": 109.69,
      "price_eur_kwh": 0.1097,
      "price_cent_kwh": 10.97
    },
    {
      "hour": 23,
      "datetime": "2026-03-18T22:00:00+01:00",
      "price_eur_mwh": 108.09,
      "price_eur_kwh": 0.1081,
      "price_cent_kwh": 10.81
    },
    {
      "hour": 24,
      "datetime": "2026-03-18T23:00:00+01:00",
      "price_eur_mwh": 99.85,
      "price_eur_kwh": 0.0998,
      "price_cent_kwh": 9.98
    }
  ]
}