{
  "metadata": {
    "source": "ENTSO-E Transparency Platform",
    "retrieved_at": "2026-02-27T15:08:31.149388",
    "timezone": "Europe/Brussels",
    "available_days": 2,
    "primary_date": "2026-02-27"
  },
  "days": {
    "today": {
      "metadata": {
        "source": "ENTSO-E Transparency Platform",
        "date": "2026-02-27",
        "retrieved_at": "2026-02-27T15:08:30.409793",
        "timezone": "Europe/Brussels",
        "data_points": 24,
        "resolution": "PT60M",
        "statistics": {
          "average_eur_mwh": 55.33,
          "min_eur_mwh": 9.09,
          "max_eur_mwh": 94.65,
          "min_hour": 13,
          "max_hour": 20,
          "price_spread": 85.56
        },
        "cheapest_blocks": {
          "1_hour": {
            "hour": 13,
            "time": "2026-02-27T12:00:00+01:00",
            "price": 9.09
          },
          "2_hours": {
            "start_hour": 12,
            "end_hour": 13,
            "start_time": "2026-02-27T11:00:00+01:00",
            "end_time": "2026-02-27T12:00:00+01:00",
            "average_price": 9.53,
            "hours": 2
          },
          "3_hours": {
            "start_hour": 12,
            "end_hour": 14,
            "start_time": "2026-02-27T11:00:00+01:00",
            "end_time": "2026-02-27T13:00:00+01:00",
            "average_price": 12.1,
            "hours": 3
          },
          "4_hours": {
            "start_hour": 12,
            "end_hour": 15,
            "start_time": "2026-02-27T11:00:00+01:00",
            "end_time": "2026-02-27T14:00:00+01:00",
            "average_price": 16.19,
            "hours": 4
          }
        }
      },
      "prices": [
        {
          "hour": 1,
          "datetime": "2026-02-27T00:00:00+01:00",
          "price_eur_mwh": 43.88,
          "price_eur_kwh": 0.0439,
          "price_cent_kwh": 4.39
        },
        {
          "hour": 2,
          "datetime": "2026-02-27T01:00:00+01:00",
          "price_eur_mwh": 44.75,
          "price_eur_kwh": 0.0447,
          "price_cent_kwh": 4.47
        },
        {
          "hour": 3,
          "datetime": "2026-02-27T02:00:00+01:00",
          "price_eur_mwh": 45.88,
          "price_eur_kwh": 0.0459,
          "price_cent_kwh": 4.59
        },
        {
          "hour": 4,
          "datetime": "2026-02-27T03:00:00+01:00",
          "price_eur_mwh": 46.22,
          "price_eur_kwh": 0.0462,
          "price_cent_kwh": 4.62
        },
        {
          "hour": 5,
          "datetime": "2026-02-27T04:00:00+01:00",
          "price_eur_mwh": 47.73,
          "price_eur_kwh": 0.0477,
          "price_cent_kwh": 4.77
        },
        {
          "hour": 6,
          "datetime": "2026-02-27T05:00:00+01:00",
          "price_eur_mwh": 52.8,
          "price_eur_kwh": 0.0528,
          "price_cent_kwh": 5.28
        },
        {
          "hour": 7,
          "datetime": "2026-02-27T06:00:00+01:00",
          "price_eur_mwh": 64.14,
          "price_eur_kwh": 0.0641,
          "price_cent_kwh": 6.41
        },
        {
          "hour": 8,
          "datetime": "2026-02-27T07:00:00+01:00",
          "price_eur_mwh": 74.11,
          "price_eur_kwh": 0.0741,
          "price_cent_kwh": 7.41
        },
        {
          "hour": 9,
          "datetime": "2026-02-27T08:00:00+01:00",
          "price_eur_mwh": 65.49,
          "price_eur_kwh": 0.0655,
          "price_cent_kwh": 6.55
        },
        {
          "hour": 10,
          "datetime": "2026-02-27T09:00:00+01:00",
          "price_eur_mwh": 53.28,
          "price_eur_kwh": 0.0533,
          "price_cent_kwh": 5.33
        },
        {
          "hour": 11,
          "datetime": "2026-02-27T10:00:00+01:00",
          "price_eur_mwh": 29.86,
          "price_eur_kwh": 0.0299,
          "price_cent_kwh": 2.99
        },
        {
          "hour": 12,
          "datetime": "2026-02-27T11:00:00+01:00",
          "price_eur_mwh": 9.97,
          "price_eur_kwh": 0.01,
          "price_cent_kwh": 1.0
        },
        {
          "hour": 13,
          "datetime": "2026-02-27T12:00:00+01:00",
          "price_eur_mwh": 9.09,
          "price_eur_kwh": 0.0091,
          "price_cent_kwh": 0.91
        },
        {
          "hour": 14,
          "datetime": "2026-02-27T13:00:00+01:00",
          "price_eur_mwh": 17.25,
          "price_eur_kwh": 0.0173,
          "price_cent_kwh": 1.73
        },
        {
          "hour": 15,
          "datetime": "2026-02-27T14:00:00+01:00",
          "price_eur_mwh": 28.43,
          "price_eur_kwh": 0.0284,
          "price_cent_kwh": 2.84
        },
        {
          "hour": 16,
          "datetime": "2026-02-27T15:00:00+01:00",
          "price_eur_mwh": 54.55,
          "price_eur_kwh": 0.0546,
          "price_cent_kwh": 5.46
        },
        {
          "hour": 17,
          "datetime": "2026-02-27T16:00:00+01:00",
          "price_eur_mwh": 72.74,
          "price_eur_kwh": 0.0727,
          "price_cent_kwh": 7.27
        },
        {
          "hour": 18,
          "datetime": "2026-02-27T17:00:00+01:00",
          "price_eur_mwh": 88.35,
          "price_eur_kwh": 0.0884,
          "price_cent_kwh": 8.84
        },
        {
          "hour": 19,
          "datetime": "2026-02-27T18:00:00+01:00",
          "price_eur_mwh": 94.55,
          "price_eur_kwh": 0.0945,
          "price_cent_kwh": 9.45
        },
        {
          "hour": 20,
          "datetime": "2026-02-27T19:00:00+01:00",
          "price_eur_mwh": 94.65,
          "price_eur_kwh": 0.0946,
          "price_cent_kwh": 9.46
        },
        {
          "hour": 21,
          "datetime": "2026-02-27T20:00:00+01:00",
          "price_eur_mwh": 79.4,
          "price_eur_kwh": 0.0794,
          "price_cent_kwh": 7.94
        },
        {
          "hour": 22,
          "datetime": "2026-02-27T21:00:00+01:00",
          "price_eur_mwh": 70.14,
          "price_eur_kwh": 0.0701,
          "price_cent_kwh": 7.01
        },
        {
          "hour": 23,
          "datetime": "2026-02-27T22:00:00+01:00",
          "price_eur_mwh": 72.87,
          "price_eur_kwh": 0.0729,
          "price_cent_kwh": 7.29
        },
        {
          "hour": 24,
          "datetime": "2026-02-27T23:00:00+01:00",
          "price_eur_mwh": 67.88,
          "price_eur_kwh": 0.0679,
          "price_cent_kwh": 6.79
        }
      ]
    },
    "tomorrow": {
      "metadata": {
        "source": "ENTSO-E Transparency Platform",
        "date": "2026-02-28",
        "retrieved_at": "2026-02-27T15:08:31.148123",
        "timezone": "Europe/Brussels",
        "data_points": 24,
        "resolution": "PT60M",
        "statistics": {
          "average_eur_mwh": 45.81,
          "min_eur_mwh": -0.02,
          "max_eur_mwh": 89.97,
          "min_hour": 12,
          "max_hour": 20,
          "price_spread": 89.99
        },
        "cheapest_blocks": {
          "1_hour": {
            "hour": 12,
            "time": "2026-02-28T11:00:00+01:00",
            "price": -0.02
          },
          "2_hours": {
            "start_hour": 12,
            "end_hour": 13,
            "start_time": "2026-02-28T11:00:00+01:00",
            "end_time": "2026-02-28T12:00:00+01:00",
            "average_price": 0.04,
            "hours": 2
          },
          "3_hours": {
            "start_hour": 12,
            "end_hour": 14,
            "start_time": "2026-02-28T11:00:00+01:00",
            "end_time": "2026-02-28T13:00:00+01:00",
            "average_price": 0.05,
            "hours": 3
          },
          "4_hours": {
            "start_hour": 12,
            "end_hour": 15,
            "start_time": "2026-02-28T11:00:00+01:00",
            "end_time": "2026-02-28T14:00:00+01:00",
            "average_price": 0.04,
            "hours": 4
          }
        }
      },
      "prices": [
        {
          "hour": 1,
          "datetime": "2026-02-28T00:00:00+01:00",
          "price_eur_mwh": 63.97,
          "price_eur_kwh": 0.064,
          "price_cent_kwh": 6.4
        },
        {
          "hour": 2,
          "datetime": "2026-02-28T01:00:00+01:00",
          "price_eur_mwh": 58.07,
          "price_eur_kwh": 0.0581,
          "price_cent_kwh": 5.81
        },
        {
          "hour": 3,
          "datetime": "2026-02-28T02:00:00+01:00",
          "price_eur_mwh": 56.03,
          "price_eur_kwh": 0.056,
          "price_cent_kwh": 5.6
        },
        {
          "hour": 4,
          "datetime": "2026-02-28T03:00:00+01:00",
          "price_eur_mwh": 52.74,
          "price_eur_kwh": 0.0527,
          "price_cent_kwh": 5.27
        },
        {
          "hour": 5,
          "datetime": "2026-02-28T04:00:00+01:00",
          "price_eur_mwh": 52.81,
          "price_eur_kwh": 0.0528,
          "price_cent_kwh": 5.28
        },
        {
          "hour": 6,
          "datetime": "2026-02-28T05:00:00+01:00",
          "price_eur_mwh": 53.07,
          "price_eur_kwh": 0.0531,
          "price_cent_kwh": 5.31
        },
        {
          "hour": 7,
          "datetime": "2026-02-28T06:00:00+01:00",
          "price_eur_mwh": 55.77,
          "price_eur_kwh": 0.0558,
          "price_cent_kwh": 5.58
        },
        {
          "hour": 8,
          "datetime": "2026-02-28T07:00:00+01:00",
          "price_eur_mwh": 56.82,
          "price_eur_kwh": 0.0568,
          "price_cent_kwh": 5.68
        },
        {
          "hour": 9,
          "datetime": "2026-02-28T08:00:00+01:00",
          "price_eur_mwh": 42.28,
          "price_eur_kwh": 0.0423,
          "price_cent_kwh": 4.23
        },
        {
          "hour": 10,
          "datetime": "2026-02-28T09:00:00+01:00",
          "price_eur_mwh": 16.17,
          "price_eur_kwh": 0.0162,
          "price_cent_kwh": 1.62
        },
        {
          "hour": 11,
          "datetime": "2026-02-28T10:00:00+01:00",
          "price_eur_mwh": 0.45,
          "price_eur_kwh": 0.0004,
          "price_cent_kwh": 0.04
        },
        {
          "hour": 12,
          "datetime": "2026-02-28T11:00:00+01:00",
          "price_eur_mwh": -0.02,
          "price_eur_kwh": -0.0,
          "price_cent_kwh": -0.0
        },
        {
          "hour": 13,
          "datetime": "2026-02-28T12:00:00+01:00",
          "price_eur_mwh": 0.1,
          "price_eur_kwh": 0.0001,
          "price_cent_kwh": 0.01
        },
        {
          "hour": 14,
          "datetime": "2026-02-28T13:00:00+01:00",
          "price_eur_mwh": 0.09,
          "price_eur_kwh": 0.0001,
          "price_cent_kwh": 0.01
        },
        {
          "hour": 15,
          "datetime": "2026-02-28T14:00:00+01:00",
          "price_eur_mwh": -0.0,
          "price_eur_kwh": -0.0,
          "price_cent_kwh": -0.0
        },
        {
          "hour": 16,
          "datetime": "2026-02-28T15:00:00+01:00",
          "price_eur_mwh": 11.39,
          "price_eur_kwh": 0.0114,
          "price_cent_kwh": 1.14
        },
        {
          "hour": 17,
          "datetime": "2026-02-28T16:00:00+01:00",
          "price_eur_mwh": 50.19,
          "price_eur_kwh": 0.0502,
          "price_cent_kwh": 5.02
        },
        {
          "hour": 18,
          "datetime": "2026-02-28T17:00:00+01:00",
          "price_eur_mwh": 71.92,
          "price_eur_kwh": 0.0719,
          "price_cent_kwh": 7.19
        },
        {
          "hour": 19,
          "datetime": "2026-02-28T18:00:00+01:00",
          "price_eur_mwh": 82.72,
          "price_eur_kwh": 0.0827,
          "price_cent_kwh": 8.27
        },
        {
          "hour": 20,
          "datetime": "2026-02-28T19:00:00+01:00",
          "price_eur_mwh": 89.97,
          "price_eur_kwh": 0.09,
          "price_cent_kwh": 9.0
        },
        {
          "hour": 21,
          "datetime": "2026-02-28T20:00:00+01:00",
          "price_eur_mwh": 74.83,
          "price_eur_kwh": 0.0748,
          "price_cent_kwh": 7.48
        },
        {
          "hour": 22,
          "datetime": "2026-02-28T21:00:00+01:00",
          "price_eur_mwh": 71.05,
          "price_eur_kwh": 0.071,
          "price_cent_kwh": 7.1
        },
        {
          "hour": 23,
          "datetime": "2026-02-28T22:00:00+01:00",
          "price_eur_mwh": 72.58,
          "price_eur_kwh": 0.0726,
          "price_cent_kwh": 7.26
        },
        {
          "hour": 24,
          "datetime": "2026-02-28T23:00:00+01:00",
          "price_eur_mwh": 66.41,
          "price_eur_kwh": 0.0664,
          "price_cent_kwh": 6.64
        }
      ]
    }
  }
}