{
  "metadata": {
    "source": "ENTSO-E Transparency Platform",
    "retrieved_at": "2026-02-22T14:57:52.424715",
    "timezone": "Europe/Brussels",
    "available_days": 2,
    "primary_date": "2026-02-22"
  },
  "days": {
    "today": {
      "metadata": {
        "source": "ENTSO-E Transparency Platform",
        "date": "2026-02-22",
        "retrieved_at": "2026-02-22T14:57:51.376335",
        "timezone": "Europe/Brussels",
        "data_points": 24,
        "resolution": "PT60M",
        "statistics": {
          "average_eur_mwh": 43.92,
          "min_eur_mwh": 28.1,
          "max_eur_mwh": 77.42,
          "min_hour": 7,
          "max_hour": 20,
          "price_spread": 49.32
        },
        "cheapest_blocks": {
          "1_hour": {
            "hour": 7,
            "time": "2026-02-22T06:00:00+01:00",
            "price": 28.1
          },
          "2_hours": {
            "start_hour": 6,
            "end_hour": 7,
            "start_time": "2026-02-22T05:00:00+01:00",
            "end_time": "2026-02-22T06:00:00+01:00",
            "average_price": 29.08,
            "hours": 2
          },
          "3_hours": {
            "start_hour": 5,
            "end_hour": 7,
            "start_time": "2026-02-22T04:00:00+01:00",
            "end_time": "2026-02-22T06:00:00+01:00",
            "average_price": 29.51,
            "hours": 3
          },
          "4_hours": {
            "start_hour": 5,
            "end_hour": 8,
            "start_time": "2026-02-22T04:00:00+01:00",
            "end_time": "2026-02-22T07:00:00+01:00",
            "average_price": 30.12,
            "hours": 4
          }
        }
      },
      "prices": [
        {
          "hour": 1,
          "datetime": "2026-02-22T00:00:00+01:00",
          "price_eur_mwh": 43.95,
          "price_eur_kwh": 0.044,
          "price_cent_kwh": 4.4
        },
        {
          "hour": 2,
          "datetime": "2026-02-22T01:00:00+01:00",
          "price_eur_mwh": 41.54,
          "price_eur_kwh": 0.0415,
          "price_cent_kwh": 4.15
        },
        {
          "hour": 3,
          "datetime": "2026-02-22T02:00:00+01:00",
          "price_eur_mwh": 37.52,
          "price_eur_kwh": 0.0375,
          "price_cent_kwh": 3.75
        },
        {
          "hour": 4,
          "datetime": "2026-02-22T03:00:00+01:00",
          "price_eur_mwh": 32.27,
          "price_eur_kwh": 0.0323,
          "price_cent_kwh": 3.23
        },
        {
          "hour": 5,
          "datetime": "2026-02-22T04:00:00+01:00",
          "price_eur_mwh": 30.35,
          "price_eur_kwh": 0.0304,
          "price_cent_kwh": 3.04
        },
        {
          "hour": 6,
          "datetime": "2026-02-22T05:00:00+01:00",
          "price_eur_mwh": 30.06,
          "price_eur_kwh": 0.0301,
          "price_cent_kwh": 3.01
        },
        {
          "hour": 7,
          "datetime": "2026-02-22T06:00:00+01:00",
          "price_eur_mwh": 28.1,
          "price_eur_kwh": 0.0281,
          "price_cent_kwh": 2.81
        },
        {
          "hour": 8,
          "datetime": "2026-02-22T07:00:00+01:00",
          "price_eur_mwh": 31.95,
          "price_eur_kwh": 0.032,
          "price_cent_kwh": 3.2
        },
        {
          "hour": 9,
          "datetime": "2026-02-22T08:00:00+01:00",
          "price_eur_mwh": 36.01,
          "price_eur_kwh": 0.036,
          "price_cent_kwh": 3.6
        },
        {
          "hour": 10,
          "datetime": "2026-02-22T09:00:00+01:00",
          "price_eur_mwh": 40.85,
          "price_eur_kwh": 0.0408,
          "price_cent_kwh": 4.08
        },
        {
          "hour": 11,
          "datetime": "2026-02-22T10:00:00+01:00",
          "price_eur_mwh": 42.01,
          "price_eur_kwh": 0.042,
          "price_cent_kwh": 4.2
        },
        {
          "hour": 12,
          "datetime": "2026-02-22T11:00:00+01:00",
          "price_eur_mwh": 39.63,
          "price_eur_kwh": 0.0396,
          "price_cent_kwh": 3.96
        },
        {
          "hour": 13,
          "datetime": "2026-02-22T12:00:00+01:00",
          "price_eur_mwh": 36.88,
          "price_eur_kwh": 0.0369,
          "price_cent_kwh": 3.69
        },
        {
          "hour": 14,
          "datetime": "2026-02-22T13:00:00+01:00",
          "price_eur_mwh": 33.78,
          "price_eur_kwh": 0.0338,
          "price_cent_kwh": 3.38
        },
        {
          "hour": 15,
          "datetime": "2026-02-22T14:00:00+01:00",
          "price_eur_mwh": 32.63,
          "price_eur_kwh": 0.0326,
          "price_cent_kwh": 3.26
        },
        {
          "hour": 16,
          "datetime": "2026-02-22T15:00:00+01:00",
          "price_eur_mwh": 36.08,
          "price_eur_kwh": 0.0361,
          "price_cent_kwh": 3.61
        },
        {
          "hour": 17,
          "datetime": "2026-02-22T16:00:00+01:00",
          "price_eur_mwh": 46.63,
          "price_eur_kwh": 0.0466,
          "price_cent_kwh": 4.66
        },
        {
          "hour": 18,
          "datetime": "2026-02-22T17:00:00+01:00",
          "price_eur_mwh": 64.01,
          "price_eur_kwh": 0.064,
          "price_cent_kwh": 6.4
        },
        {
          "hour": 19,
          "datetime": "2026-02-22T18:00:00+01:00",
          "price_eur_mwh": 72.86,
          "price_eur_kwh": 0.0729,
          "price_cent_kwh": 7.29
        },
        {
          "hour": 20,
          "datetime": "2026-02-22T19:00:00+01:00",
          "price_eur_mwh": 77.42,
          "price_eur_kwh": 0.0774,
          "price_cent_kwh": 7.74
        },
        {
          "hour": 21,
          "datetime": "2026-02-22T20:00:00+01:00",
          "price_eur_mwh": 65.09,
          "price_eur_kwh": 0.0651,
          "price_cent_kwh": 6.51
        },
        {
          "hour": 22,
          "datetime": "2026-02-22T21:00:00+01:00",
          "price_eur_mwh": 55.41,
          "price_eur_kwh": 0.0554,
          "price_cent_kwh": 5.54
        },
        {
          "hour": 23,
          "datetime": "2026-02-22T22:00:00+01:00",
          "price_eur_mwh": 56.53,
          "price_eur_kwh": 0.0565,
          "price_cent_kwh": 5.65
        },
        {
          "hour": 24,
          "datetime": "2026-02-22T23:00:00+01:00",
          "price_eur_mwh": 42.47,
          "price_eur_kwh": 0.0425,
          "price_cent_kwh": 4.25
        }
      ]
    },
    "tomorrow": {
      "metadata": {
        "source": "ENTSO-E Transparency Platform",
        "date": "2026-02-23",
        "retrieved_at": "2026-02-22T14:57:52.423485",
        "timezone": "Europe/Brussels",
        "data_points": 24,
        "resolution": "PT60M",
        "statistics": {
          "average_eur_mwh": 58.38,
          "min_eur_mwh": 5.31,
          "max_eur_mwh": 112.74,
          "min_hour": 14,
          "max_hour": 20,
          "price_spread": 107.43
        },
        "cheapest_blocks": {
          "1_hour": {
            "hour": 14,
            "time": "2026-02-23T13:00:00+01:00",
            "price": 5.31
          },
          "2_hours": {
            "start_hour": 13,
            "end_hour": 14,
            "start_time": "2026-02-23T12:00:00+01:00",
            "end_time": "2026-02-23T13:00:00+01:00",
            "average_price": 6.99,
            "hours": 2
          },
          "3_hours": {
            "start_hour": 13,
            "end_hour": 15,
            "start_time": "2026-02-23T12:00:00+01:00",
            "end_time": "2026-02-23T14:00:00+01:00",
            "average_price": 13.63,
            "hours": 3
          },
          "4_hours": {
            "start_hour": 12,
            "end_hour": 15,
            "start_time": "2026-02-23T11:00:00+01:00",
            "end_time": "2026-02-23T14:00:00+01:00",
            "average_price": 19.34,
            "hours": 4
          }
        }
      },
      "prices": [
        {
          "hour": 1,
          "datetime": "2026-02-23T00:00:00+01:00",
          "price_eur_mwh": 37.36,
          "price_eur_kwh": 0.0374,
          "price_cent_kwh": 3.74
        },
        {
          "hour": 2,
          "datetime": "2026-02-23T01:00:00+01:00",
          "price_eur_mwh": 37.28,
          "price_eur_kwh": 0.0373,
          "price_cent_kwh": 3.73
        },
        {
          "hour": 3,
          "datetime": "2026-02-23T02:00:00+01:00",
          "price_eur_mwh": 37.08,
          "price_eur_kwh": 0.0371,
          "price_cent_kwh": 3.71
        },
        {
          "hour": 4,
          "datetime": "2026-02-23T03:00:00+01:00",
          "price_eur_mwh": 36.0,
          "price_eur_kwh": 0.036,
          "price_cent_kwh": 3.6
        },
        {
          "hour": 5,
          "datetime": "2026-02-23T04:00:00+01:00",
          "price_eur_mwh": 36.16,
          "price_eur_kwh": 0.0362,
          "price_cent_kwh": 3.62
        },
        {
          "hour": 6,
          "datetime": "2026-02-23T05:00:00+01:00",
          "price_eur_mwh": 45.83,
          "price_eur_kwh": 0.0458,
          "price_cent_kwh": 4.58
        },
        {
          "hour": 7,
          "datetime": "2026-02-23T06:00:00+01:00",
          "price_eur_mwh": 64.42,
          "price_eur_kwh": 0.0644,
          "price_cent_kwh": 6.44
        },
        {
          "hour": 8,
          "datetime": "2026-02-23T07:00:00+01:00",
          "price_eur_mwh": 86.88,
          "price_eur_kwh": 0.0869,
          "price_cent_kwh": 8.69
        },
        {
          "hour": 9,
          "datetime": "2026-02-23T08:00:00+01:00",
          "price_eur_mwh": 89.27,
          "price_eur_kwh": 0.0893,
          "price_cent_kwh": 8.93
        },
        {
          "hour": 10,
          "datetime": "2026-02-23T09:00:00+01:00",
          "price_eur_mwh": 71.48,
          "price_eur_kwh": 0.0715,
          "price_cent_kwh": 7.15
        },
        {
          "hour": 11,
          "datetime": "2026-02-23T10:00:00+01:00",
          "price_eur_mwh": 50.89,
          "price_eur_kwh": 0.0509,
          "price_cent_kwh": 5.09
        },
        {
          "hour": 12,
          "datetime": "2026-02-23T11:00:00+01:00",
          "price_eur_mwh": 36.48,
          "price_eur_kwh": 0.0365,
          "price_cent_kwh": 3.65
        },
        {
          "hour": 13,
          "datetime": "2026-02-23T12:00:00+01:00",
          "price_eur_mwh": 8.68,
          "price_eur_kwh": 0.0087,
          "price_cent_kwh": 0.87
        },
        {
          "hour": 14,
          "datetime": "2026-02-23T13:00:00+01:00",
          "price_eur_mwh": 5.31,
          "price_eur_kwh": 0.0053,
          "price_cent_kwh": 0.53
        },
        {
          "hour": 15,
          "datetime": "2026-02-23T14:00:00+01:00",
          "price_eur_mwh": 26.89,
          "price_eur_kwh": 0.0269,
          "price_cent_kwh": 2.69
        },
        {
          "hour": 16,
          "datetime": "2026-02-23T15:00:00+01:00",
          "price_eur_mwh": 43.87,
          "price_eur_kwh": 0.0439,
          "price_cent_kwh": 4.39
        },
        {
          "hour": 17,
          "datetime": "2026-02-23T16:00:00+01:00",
          "price_eur_mwh": 63.06,
          "price_eur_kwh": 0.0631,
          "price_cent_kwh": 6.31
        },
        {
          "hour": 18,
          "datetime": "2026-02-23T17:00:00+01:00",
          "price_eur_mwh": 77.5,
          "price_eur_kwh": 0.0775,
          "price_cent_kwh": 7.75
        },
        {
          "hour": 19,
          "datetime": "2026-02-23T18:00:00+01:00",
          "price_eur_mwh": 100.08,
          "price_eur_kwh": 0.1001,
          "price_cent_kwh": 10.01
        },
        {
          "hour": 20,
          "datetime": "2026-02-23T19:00:00+01:00",
          "price_eur_mwh": 112.74,
          "price_eur_kwh": 0.1127,
          "price_cent_kwh": 11.27
        },
        {
          "hour": 21,
          "datetime": "2026-02-23T20:00:00+01:00",
          "price_eur_mwh": 97.31,
          "price_eur_kwh": 0.0973,
          "price_cent_kwh": 9.73
        },
        {
          "hour": 22,
          "datetime": "2026-02-23T21:00:00+01:00",
          "price_eur_mwh": 82.55,
          "price_eur_kwh": 0.0825,
          "price_cent_kwh": 8.25
        },
        {
          "hour": 23,
          "datetime": "2026-02-23T22:00:00+01:00",
          "price_eur_mwh": 81.4,
          "price_eur_kwh": 0.0814,
          "price_cent_kwh": 8.14
        },
        {
          "hour": 24,
          "datetime": "2026-02-23T23:00:00+01:00",
          "price_eur_mwh": 72.67,
          "price_eur_kwh": 0.0727,
          "price_cent_kwh": 7.27
        }
      ]
    }
  }
}